myfunctions_EMIL8708/__init__.py
myfunctions_EMIL8708/math.py
myfunctions_EMIL8708-0.0.16.dist-info/METADATA
myfunctions_EMIL8708-0.0.16.dist-info/WHEEL
myfunctions_EMIL8708-0.0.16.dist-info/top_level.txt
myfunctions_EMIL8708-0.0.16.dist-info/RECORD
