Metadata-Version: 2.1
Name: myfunctions-EMIL8708
Version: 0.0.16
Summary: A description of your package
Home-page: https://github.com/EMIL8708
Author: Emil Moldoisaev
Author-email: moldoisaemil@gmail.com
License: MIT
Platform: UNKNOWN
Classifier: Programming Language :: Python :: 3
Classifier: License :: OSI Approved :: MIT License
Classifier: Operating System :: OS Independent
Requires-Python: >=3.6
